git_draft/__init__.py
git_draft/__main__.py
git_draft/bots/__init__.py
git_draft/bots/claude_code.py
git_draft/bots/common.py
git_draft/bots/openai_api/__init__.py
git_draft/bots/openai_api/assistants.py
git_draft/bots/openai_api/common.py
git_draft/bots/openai_api/completions.py
git_draft/bots/openai_api/responses.py
git_draft/common.py
git_draft/drafter.py
git_draft/editor.py
git_draft/events/__init__.py
git_draft/events/common.py
git_draft/events/feedback_events.py
git_draft/events/worktree_events.py
git_draft/git.py
git_draft/instructions.py
git_draft/progress.py
git_draft/prompt.py
git_draft/prompts/.LAYOUTS/docopt.jinja
git_draft/prompts/.MACROS.jinja
git_draft/prompts/add-docstrings.jinja
git_draft/prompts/add-test.jinja
git_draft/py.typed
git_draft/queries/add-action-event.sql
git_draft/queries/add-action-summary.sql
git_draft/queries/add-folio.sql
git_draft/queries/add-prompt.sql
git_draft/queries/create-tables.sql
git_draft/queries/get-folio-by-id.sql
git_draft/queries/get-latest-folio-prompt.sql
git_draft/queries/list-action-events.sql
git_draft/queries/list-folio-prompts.sql
git_draft/queries/list-folios.sql
git_draft/store.py
git_draft/worktrees.py
git_draft-0.53.0.dist-info/LICENSE
git_draft-0.53.0.dist-info/METADATA
git_draft-0.53.0.dist-info/WHEEL
git_draft-0.53.0.dist-info/entry_points.txt
git_draft-0.53.0.dist-info/RECORD
