Metadata-Version: 2.3
Name: git-draft
Version: 0.53.0
Summary: Version-controlled code assistant
License: MIT
Author: Matthieu Monsch
Author-email: mtth@apache.org
Requires-Python: >=3.12
Classifier: License :: OSI Approved :: MIT License
Classifier: Programming Language :: Python :: 3
Classifier: Programming Language :: Python :: 3.12
Classifier: Programming Language :: Python :: 3.13
Provides-Extra: claude-code
Provides-Extra: openai
Requires-Dist: claude-code-sdk (==0.0.22) ; extra == "claude-code"
Requires-Dist: docopt-ng (>=0.9,<0.10)
Requires-Dist: jinja2 (>=3.1.5,<4)
Requires-Dist: msgspec (>=0.19.0,<0.20.0)
Requires-Dist: openai (>=1.64.0,<2) ; extra == "openai"
Requires-Dist: xdg-base-dirs (>=6.0.2,<7)
Requires-Dist: yaspin (>=3.1.0,<4)
Project-URL: Documentation, https://mtth.github.io/git-draft
Project-URL: Repository, https://github.com/mtth/git-draft
